<?xml version="1.0" encoding="ISO-8859-1"?>
<MER>
	<Informacoes>
		<Posicao Left="0" Top="546"/>
		<TotalItens Valor="34"/>
		<Tipo Valor="LÓGICO"/>
		<Versao Valor="2.0.0"/>
		<Autor Valor=""/>
		<Observacao Valor=""/>
		<Template>
      <CAMPOS/>
      <TIPOS>
        <ITEM>
          <Campo1>Date</Campo1>
          <Campo2>DATE</Campo2>
        </ITEM>
      </TIPOS>
      <COMPLEMENTO_CAMPOS/>
      <COMPLEMENTO_TABELAS/>
      <DDL>
        <CTab_A>CREATE TABLE *$nome_tabela</CTab_A>
        <CTab_B> (</CTab_B>
        <CTab_Compl>*$compl_tabela</CTab_Compl>
        <CTab_C>)*$separador*$\n</CTab_C>
        <CCamp>*$nome_campo *$tipo_campo *$compl_campo</CCamp>
        <Pk_inTab>-1</Pk_inTab>
        <Fk_inTab>-1</Fk_inTab>
        <Const_Nomear>0</Const_Nomear>
        <CConst_Nome>*$nome_tabela_*$envol_campo</CConst_Nome>
        <Separador></Separador>
      </DDL>
    </Template>
	</Informacoes>
	<Tabelas>
    <Tabela nome="Produto" id="1">
      <Left Valor="242"/>
      <Top Valor="694"/>
      <Width Valor="172"/>
      <Height Valor="118"/>
      <Fonte default="-1"/>
      <Dicionario></Dicionario>
      <Nula Valor="0"/>
      <Observacao></Observacao>
      <Futuro></Futuro>
      <Anexos/>
      <Color Valor="12639424"/>
      <Complemento Valor=""/>
      <cOrdem Valor="0"/>
      <Campos>
        <Campo nome="IdProduto" id="5">
          <Left Valor="242"/>
          <Top Valor="713"/>
          <Width Valor="170"/>
          <Height Valor="19"/>
          <Fonte default="-1"/>
          <Dicionario></Dicionario>
          <Nula Valor="-1"/>
          <Observacao></Observacao>
          <Futuro></Futuro>
          <Anexos/>
          <ApenasSeparador Valor="0"/>
          <IsKey Valor="-1"/>
          <IsFKey Valor="0"/>
          <Tipo Valor="INT"/>
          <TabOrigem Valor="0"/>
          <CampoOrigem Valor="0"/>
          <Complemento Valor=""/>
          <OnUpdate Valor="0"/>
          <OnDelete Valor="0"/>
        </Campo>
        <Campo nome="Valor" id="6">
          <Left Valor="242"/>
          <Top Valor="731"/>
          <Width Valor="170"/>
          <Height Valor="19"/>
          <Fonte default="-1"/>
          <Dicionario></Dicionario>
          <Nula Valor="-1"/>
          <Observacao></Observacao>
          <Futuro></Futuro>
          <Anexos/>
          <ApenasSeparador Valor="0"/>
          <IsKey Valor="0"/>
          <IsFKey Valor="0"/>
          <Tipo Valor="FLOAT"/>
          <TabOrigem Valor="0"/>
          <CampoOrigem Valor="0"/>
          <Complemento Valor=""/>
          <OnUpdate Valor="0"/>
          <OnDelete Valor="0"/>
        </Campo>
        <Campo nome="Nome" id="7">
          <Left Valor="242"/>
          <Top Valor="749"/>
          <Width Valor="170"/>
          <Height Valor="19"/>
          <Fonte default="-1"/>
          <Dicionario></Dicionario>
          <Nula Valor="-1"/>
          <Observacao></Observacao>
          <Futuro></Futuro>
          <Anexos/>
          <ApenasSeparador Valor="0"/>
          <IsKey Valor="0"/>
          <IsFKey Valor="0"/>
          <Tipo Valor="VARCHAR(50)"/>
          <TabOrigem Valor="0"/>
          <CampoOrigem Valor="0"/>
          <Complemento Valor=""/>
          <OnUpdate Valor="0"/>
          <OnDelete Valor="0"/>
        </Campo>
        <Campo nome="Marca" id="8">
          <Left Valor="242"/>
          <Top Valor="767"/>
          <Width Valor="170"/>
          <Height Valor="19"/>
          <Fonte default="-1"/>
          <Dicionario></Dicionario>
          <Nula Valor="-1"/>
          <Observacao></Observacao>
          <Futuro></Futuro>
          <Anexos/>
          <ApenasSeparador Valor="0"/>
          <IsKey Valor="0"/>
          <IsFKey Valor="0"/>
          <Tipo Valor="VARCHAR(50)"/>
          <TabOrigem Valor="0"/>
          <CampoOrigem Valor="0"/>
          <Complemento Valor=""/>
          <OnUpdate Valor="0"/>
          <OnDelete Valor="0"/>
        </Campo>
        <Campo nome="Descricao" id="9">
          <Left Valor="242"/>
          <Top Valor="785"/>
          <Width Valor="170"/>
          <Height Valor="19"/>
          <Fonte default="-1"/>
          <Dicionario></Dicionario>
          <Nula Valor="-1"/>
          <Observacao></Observacao>
          <Futuro></Futuro>
          <Anexos/>
          <ApenasSeparador Valor="0"/>
          <IsKey Valor="0"/>
          <IsFKey Valor="0"/>
          <Tipo Valor="VARCHAR(150)"/>
          <TabOrigem Valor="0"/>
          <CampoOrigem Valor="0"/>
          <Complemento Valor=""/>
          <OnUpdate Valor="0"/>
          <OnDelete Valor="0"/>
        </Campo>
      </Campos>
    </Tabela>
    <Tabela nome="Estoque" id="2">
      <Left Valor="245"/>
      <Top Valor="848"/>
      <Width Valor="167"/>
      <Height Valor="104"/>
      <Fonte default="-1"/>
      <Dicionario></Dicionario>
      <Nula Valor="0"/>
      <Observacao></Observacao>
      <Futuro></Futuro>
      <Anexos/>
      <Color Valor="12639424"/>
      <Complemento Valor=""/>
      <cOrdem Valor="0"/>
      <Campos>
        <Campo nome="IdEstoque" id="36">
          <Left Valor="245"/>
          <Top Valor="867"/>
          <Width Valor="165"/>
          <Height Valor="19"/>
          <Fonte default="-1"/>
          <Dicionario></Dicionario>
          <Nula Valor="-1"/>
          <Observacao></Observacao>
          <Futuro></Futuro>
          <Anexos/>
          <ApenasSeparador Valor="0"/>
          <IsKey Valor="-1"/>
          <IsFKey Valor="-1"/>
          <Tipo Valor="INT"/>
          <TabOrigem Valor="1"/>
          <CampoOrigem Valor="5"/>
          <Complemento Valor=""/>
          <OnUpdate Valor="0"/>
          <OnDelete Valor="0"/>
        </Campo>
        <Campo nome="Quantidade" id="11">
          <Left Valor="245"/>
          <Top Valor="885"/>
          <Width Valor="165"/>
          <Height Valor="19"/>
          <Fonte default="-1"/>
          <Dicionario></Dicionario>
          <Nula Valor="-1"/>
          <Observacao></Observacao>
          <Futuro></Futuro>
          <Anexos/>
          <ApenasSeparador Valor="0"/>
          <IsKey Valor="0"/>
          <IsFKey Valor="0"/>
          <Tipo Valor="INT"/>
          <TabOrigem Valor="0"/>
          <CampoOrigem Valor="0"/>
          <Complemento Valor=""/>
          <OnUpdate Valor="0"/>
          <OnDelete Valor="0"/>
        </Campo>
        <Campo nome="qtdMinima" id="12">
          <Left Valor="245"/>
          <Top Valor="903"/>
          <Width Valor="165"/>
          <Height Valor="19"/>
          <Fonte default="-1"/>
          <Dicionario></Dicionario>
          <Nula Valor="-1"/>
          <Observacao></Observacao>
          <Futuro></Futuro>
          <Anexos/>
          <ApenasSeparador Valor="0"/>
          <IsKey Valor="0"/>
          <IsFKey Valor="0"/>
          <Tipo Valor="INT"/>
          <TabOrigem Valor="0"/>
          <CampoOrigem Valor="0"/>
          <Complemento Valor=""/>
          <OnUpdate Valor="0"/>
          <OnDelete Valor="0"/>
        </Campo>
        <Campo nome="qtdMaxima" id="13">
          <Left Valor="245"/>
          <Top Valor="921"/>
          <Width Valor="165"/>
          <Height Valor="19"/>
          <Fonte default="-1"/>
          <Dicionario></Dicionario>
          <Nula Valor="-1"/>
          <Observacao></Observacao>
          <Futuro></Futuro>
          <Anexos/>
          <ApenasSeparador Valor="0"/>
          <IsKey Valor="0"/>
          <IsFKey Valor="0"/>
          <Tipo Valor="INT"/>
          <TabOrigem Valor="0"/>
          <CampoOrigem Valor="0"/>
          <Complemento Valor=""/>
          <OnUpdate Valor="0"/>
          <OnDelete Valor="0"/>
        </Campo>
      </Campos>
    </Tabela>
    <Tabela nome="Carrinho" id="3">
      <Left Valor="261"/>
      <Top Valor="1093"/>
      <Width Valor="134"/>
      <Height Valor="118"/>
      <Fonte default="-1"/>
      <Dicionario></Dicionario>
      <Nula Valor="0"/>
      <Observacao></Observacao>
      <Futuro></Futuro>
      <Anexos/>
      <Color Valor="12639424"/>
      <Complemento Valor=""/>
      <cOrdem Valor="0"/>
      <Campos>
        <Campo nome="IdVenda" id="14">
          <Left Valor="261"/>
          <Top Valor="1112"/>
          <Width Valor="132"/>
          <Height Valor="19"/>
          <Fonte default="-1"/>
          <Dicionario></Dicionario>
          <Nula Valor="-1"/>
          <Observacao></Observacao>
          <Futuro></Futuro>
          <Anexos/>
          <ApenasSeparador Valor="0"/>
          <IsKey Valor="0"/>
          <IsFKey Valor="0"/>
          <Tipo Valor="INT"/>
          <TabOrigem Valor="0"/>
          <CampoOrigem Valor="0"/>
          <Complemento Valor=""/>
          <OnUpdate Valor="0"/>
          <OnDelete Valor="0"/>
        </Campo>
        <Campo nome="IdProduto" id="49">
          <Left Valor="261"/>
          <Top Valor="1130"/>
          <Width Valor="132"/>
          <Height Valor="19"/>
          <Fonte default="-1"/>
          <Dicionario></Dicionario>
          <Nula Valor="-1"/>
          <Observacao></Observacao>
          <Futuro></Futuro>
          <Anexos/>
          <ApenasSeparador Valor="0"/>
          <IsKey Valor="0"/>
          <IsFKey Valor="-1"/>
          <Tipo Valor="INT"/>
          <TabOrigem Valor="30"/>
          <CampoOrigem Valor="38"/>
          <Complemento Valor=""/>
          <OnUpdate Valor="0"/>
          <OnDelete Valor="0"/>
        </Campo>
        <Campo nome="Responsavel" id="15">
          <Left Valor="261"/>
          <Top Valor="1148"/>
          <Width Valor="132"/>
          <Height Valor="19"/>
          <Fonte default="-1"/>
          <Dicionario></Dicionario>
          <Nula Valor="-1"/>
          <Observacao></Observacao>
          <Futuro></Futuro>
          <Anexos/>
          <ApenasSeparador Valor="0"/>
          <IsKey Valor="0"/>
          <IsFKey Valor="0"/>
          <Tipo Valor="VARCHAR(50)"/>
          <TabOrigem Valor="0"/>
          <CampoOrigem Valor="0"/>
          <Complemento Valor=""/>
          <OnUpdate Valor="0"/>
          <OnDelete Valor="0"/>
        </Campo>
        <Campo nome="qtdComprada" id="17">
          <Left Valor="261"/>
          <Top Valor="1166"/>
          <Width Valor="132"/>
          <Height Valor="19"/>
          <Fonte default="-1"/>
          <Dicionario></Dicionario>
          <Nula Valor="-1"/>
          <Observacao></Observacao>
          <Futuro></Futuro>
          <Anexos/>
          <ApenasSeparador Valor="0"/>
          <IsKey Valor="0"/>
          <IsFKey Valor="0"/>
          <Tipo Valor="INT"/>
          <TabOrigem Valor="0"/>
          <CampoOrigem Valor="0"/>
          <Complemento Valor=""/>
          <OnUpdate Valor="0"/>
          <OnDelete Valor="0"/>
        </Campo>
        <Campo nome="Saida" id="18">
          <Left Valor="261"/>
          <Top Valor="1184"/>
          <Width Valor="132"/>
          <Height Valor="19"/>
          <Fonte default="-1"/>
          <Dicionario></Dicionario>
          <Nula Valor="-1"/>
          <Observacao></Observacao>
          <Futuro></Futuro>
          <Anexos/>
          <ApenasSeparador Valor="0"/>
          <IsKey Valor="0"/>
          <IsFKey Valor="0"/>
          <Tipo Valor="Date"/>
          <TabOrigem Valor="0"/>
          <CampoOrigem Valor="0"/>
          <Complemento Valor=""/>
          <OnUpdate Valor="0"/>
          <OnDelete Valor="0"/>
        </Campo>
      </Campos>
    </Tabela>
    <Tabela nome="Item_De_Estoque" id="30">
      <Left Valor="242"/>
      <Top Valor="990"/>
      <Width Valor="173"/>
      <Height Valor="67"/>
      <Fonte default="-1"/>
      <Dicionario></Dicionario>
      <Nula Valor="0"/>
      <Observacao></Observacao>
      <Futuro></Futuro>
      <Anexos/>
      <Color Valor="12639424"/>
      <Complemento Valor=""/>
      <cOrdem Valor="0"/>
      <Campos>
        <Campo nome="IdEstoque" id="38">
          <Left Valor="242"/>
          <Top Valor="1009"/>
          <Width Valor="171"/>
          <Height Valor="19"/>
          <Fonte default="-1"/>
          <Dicionario></Dicionario>
          <Nula Valor="-1"/>
          <Observacao></Observacao>
          <Futuro></Futuro>
          <Anexos/>
          <ApenasSeparador Valor="0"/>
          <IsKey Valor="-1"/>
          <IsFKey Valor="-1"/>
          <Tipo Valor="INT"/>
          <TabOrigem Valor="2"/>
          <CampoOrigem Valor="36"/>
          <Complemento Valor=""/>
          <OnUpdate Valor="0"/>
          <OnDelete Valor="0"/>
        </Campo>
        <Campo nome="Entrada" id="34">
          <Left Valor="242"/>
          <Top Valor="1027"/>
          <Width Valor="171"/>
          <Height Valor="19"/>
          <Fonte default="-1"/>
          <Dicionario></Dicionario>
          <Nula Valor="-1"/>
          <Observacao></Observacao>
          <Futuro></Futuro>
          <Anexos/>
          <ApenasSeparador Valor="0"/>
          <IsKey Valor="0"/>
          <IsFKey Valor="0"/>
          <Tipo Valor="Date"/>
          <TabOrigem Valor="0"/>
          <CampoOrigem Valor="0"/>
          <Complemento Valor=""/>
          <OnUpdate Valor="0"/>
          <OnDelete Valor="0"/>
        </Campo>
      </Campos>
    </Tabela>
  </Tabelas>
	<LigacaoEntreTabelas>
    <LigaTabela nome="Estoque_Produto_1" id="22">
      <Left Valor="321"/>
      <Top Valor="823"/>
      <Width Valor="15"/>
      <Height Valor="15"/>
      <Fonte default="-1"/>
      <Dicionario></Dicionario>
      <Nula Valor="0"/>
      <Observacao></Observacao>
      <Futuro></Futuro>
      <Anexos/>
      <SetaDirecao Valor="0"/>
      <Ligacoes>
        <Ligacao Destino_ID="2">
          <MostraCardinalidade Valor="-1" Card_id="23"/>
          <Cardinalidades Cardinalidade="2">
            <Cardinalidade nome="" id="23">
              <Left Valor="328"/>
              <Top Valor="833"/>
              <Width Valor="40"/>
              <Height Valor="20"/>
              <Fonte default="-1"/>
              <Dicionario></Dicionario>
              <Nula Valor="0"/>
              <Observacao></Observacao>
              <Futuro></Futuro>
              <Anexos/>
              <Cor Valor="15780518"/>
              <TamAuto Valor="-1"/>
              <Tipo Valor="0"/>
              <TextAlin Valor="0"/>
              <Card Valor="2"/>
              <Fixa Valor="0"/>
              <Ligacoes/>
            </Cardinalidade>
          </Cardinalidades>
          <Orientacao Valor="0"/>
          <Fraca Valor="0"/>
        </Ligacao>
        <Ligacao Destino_ID="1">
          <MostraCardinalidade Valor="-1" Card_id="24"/>
          <Cardinalidades Cardinalidade="4">
            <Cardinalidade nome="" id="24">
              <Left Valor="328"/>
              <Top Valor="813"/>
              <Width Valor="40"/>
              <Height Valor="20"/>
              <Fonte default="-1"/>
              <Dicionario></Dicionario>
              <Nula Valor="0"/>
              <Observacao></Observacao>
              <Futuro></Futuro>
              <Anexos/>
              <Cor Valor="15780518"/>
              <TamAuto Valor="-1"/>
              <Tipo Valor="0"/>
              <TextAlin Valor="0"/>
              <Card Valor="4"/>
              <Fixa Valor="0"/>
              <Ligacoes/>
            </Cardinalidade>
          </Cardinalidades>
          <Orientacao Valor="0"/>
          <Fraca Valor="0"/>
        </Ligacao>
      </Ligacoes>
    </LigaTabela>
    <LigaTabela nome="Estoque_Item_De_Estoque_1" id="39">
      <Left Valor="321"/>
      <Top Valor="965"/>
      <Width Valor="15"/>
      <Height Valor="15"/>
      <Fonte default="-1"/>
      <Dicionario></Dicionario>
      <Nula Valor="0"/>
      <Observacao></Observacao>
      <Futuro></Futuro>
      <Anexos/>
      <SetaDirecao Valor="0"/>
      <Ligacoes>
        <Ligacao Destino_ID="2">
          <MostraCardinalidade Valor="-1" Card_id="40"/>
          <Cardinalidades Cardinalidade="1">
            <Cardinalidade nome="" id="40">
              <Left Valor="328"/>
              <Top Valor="953"/>
              <Width Valor="40"/>
              <Height Valor="20"/>
              <Fonte default="-1"/>
              <Dicionario></Dicionario>
              <Nula Valor="0"/>
              <Observacao></Observacao>
              <Futuro></Futuro>
              <Anexos/>
              <Cor Valor="15780518"/>
              <TamAuto Valor="-1"/>
              <Tipo Valor="0"/>
              <TextAlin Valor="0"/>
              <Card Valor="1"/>
              <Fixa Valor="0"/>
              <Ligacoes/>
            </Cardinalidade>
          </Cardinalidades>
          <Orientacao Valor="0"/>
          <Fraca Valor="0"/>
        </Ligacao>
        <Ligacao Destino_ID="30">
          <MostraCardinalidade Valor="-1" Card_id="41"/>
          <Cardinalidades Cardinalidade="1">
            <Cardinalidade nome="" id="41">
              <Left Valor="328"/>
              <Top Valor="975"/>
              <Width Valor="40"/>
              <Height Valor="20"/>
              <Fonte default="-1"/>
              <Dicionario></Dicionario>
              <Nula Valor="0"/>
              <Observacao></Observacao>
              <Futuro></Futuro>
              <Anexos/>
              <Cor Valor="15780518"/>
              <TamAuto Valor="-1"/>
              <Tipo Valor="0"/>
              <TextAlin Valor="0"/>
              <Card Valor="1"/>
              <Fixa Valor="0"/>
              <Ligacoes/>
            </Cardinalidade>
          </Cardinalidades>
          <Orientacao Valor="0"/>
          <Fraca Valor="0"/>
        </Ligacao>
      </Ligacoes>
    </LigaTabela>
    <LigaTabela nome="Item_De_Estoque_Carrinho_1" id="46">
      <Left Valor="321"/>
      <Top Valor="1065"/>
      <Width Valor="15"/>
      <Height Valor="15"/>
      <Fonte default="-1"/>
      <Dicionario></Dicionario>
      <Nula Valor="0"/>
      <Observacao></Observacao>
      <Futuro></Futuro>
      <Anexos/>
      <SetaDirecao Valor="0"/>
      <Ligacoes>
        <Ligacao Destino_ID="30">
          <MostraCardinalidade Valor="-1" Card_id="47"/>
          <Cardinalidades Cardinalidade="3">
            <Cardinalidade nome="" id="47">
              <Left Valor="328"/>
              <Top Valor="1058"/>
              <Width Valor="40"/>
              <Height Valor="20"/>
              <Fonte default="-1"/>
              <Dicionario></Dicionario>
              <Nula Valor="0"/>
              <Observacao></Observacao>
              <Futuro></Futuro>
              <Anexos/>
              <Cor Valor="15780518"/>
              <TamAuto Valor="-1"/>
              <Tipo Valor="0"/>
              <TextAlin Valor="0"/>
              <Card Valor="3"/>
              <Fixa Valor="0"/>
              <Ligacoes/>
            </Cardinalidade>
          </Cardinalidades>
          <Orientacao Valor="0"/>
          <Fraca Valor="0"/>
        </Ligacao>
        <Ligacao Destino_ID="3">
          <MostraCardinalidade Valor="-1" Card_id="48"/>
          <Cardinalidades Cardinalidade="1">
            <Cardinalidade nome="" id="48">
              <Left Valor="328"/>
              <Top Valor="1078"/>
              <Width Valor="40"/>
              <Height Valor="20"/>
              <Fonte default="-1"/>
              <Dicionario></Dicionario>
              <Nula Valor="0"/>
              <Observacao></Observacao>
              <Futuro></Futuro>
              <Anexos/>
              <Cor Valor="15780518"/>
              <TamAuto Valor="-1"/>
              <Tipo Valor="0"/>
              <TextAlin Valor="0"/>
              <Card Valor="1"/>
              <Fixa Valor="0"/>
              <Ligacoes/>
            </Cardinalidade>
          </Cardinalidades>
          <Orientacao Valor="0"/>
          <Fraca Valor="0"/>
        </Ligacao>
      </Ligacoes>
    </LigaTabela>
  </LigacaoEntreTabelas>
	<Texto>
	</Texto>
</MER>
